splinterpy/__init__.py
splinterpy/bspline.py
splinterpy/bsplineboosting.py
splinterpy/bsplinebuilders.py
splinterpy/datatable.py
splinterpy/function.py
splinterpy/splinter_backend.py
splinterpy/utilities.py
splinterpy/version
splinterpy/lib/linux/x86-64/libsplinter-4-0.so
splinterpy-4.0.4.dist-info/LICENSE
splinterpy-4.0.4.dist-info/METADATA
splinterpy-4.0.4.dist-info/WHEEL
splinterpy-4.0.4.dist-info/top_level.txt
splinterpy-4.0.4.dist-info/zip-safe
splinterpy-4.0.4.dist-info/RECORD
